cba_events/__init__.py
cba_events/event_factory.py
cba_events/consumers/__init__.py
cba_events/consumers/base.py
cba_events/consumers/kafka_consumer.py
cba_events/events/__init__.py
cba_events/events/base_event.py
cba_events/events/types.py
cba_events/handlers/__init__.py
cba_events/handlers/stockpile_handler.py
cba_events/publishers/__init__.py
cba_events/publishers/base.py
cba_events/publishers/kafka.py
cba_events-0.1.22.dist-info/LICENSE
cba_events-0.1.22.dist-info/METADATA
cba_events-0.1.22.dist-info/WHEEL
cba_events-0.1.22.dist-info/top_level.txt
cba_events-0.1.22.dist-info/RECORD
