Metadata-Version: 2.2
Name: cba-events
Version: 0.1.22
Summary: A Python package for handling cba events
Author-email: Crystal Ball <your.email@example.com>
License:                     GNU GENERAL PUBLIC LICENSE
Requires-Python: >=3.8
License-File: LICENSE
Requires-Dist: confluent-kafka>=2.0.0
Requires-Dist: dataclasses-json>=0.5.7
